[
  {
    "ContainingType": "Code1.Controllers.WebServiceController",
    "Method": "CheckUser",
    "RelativePath": "api/WebService/checkUser",
    "HttpMethod": "GET",
    "IsController": true,
    "Order": 0,
    "Parameters": [
      {
        "Name": "username",
        "Type": "System.String",
        "IsRequired": false
      }
    ],
    "ReturnTypes": []
  },
  {
    "ContainingType": "Code1.Controllers.WebServiceController",
    "Method": "GetEmojis",
    "RelativePath": "api/WebService/emojis/{userId}",
    "HttpMethod": "GET",
    "IsController": true,
    "Order": 0,
    "Parameters": [
      {
        "Name": "userId",
        "Type": "System.String",
        "IsRequired": true
      }
    ],
    "ReturnTypes": []
  },
  {
    "ContainingType": "Code1.Controllers.WebServiceController",
    "Method": "AddMessage",
    "RelativePath": "api/WebService/message",
    "HttpMethod": "POST",
    "IsController": true,
    "Order": 0,
    "Parameters": [
      {
        "Name": "request",
        "Type": "Code1.Controllers.AddMessageRequest",
        "IsRequired": true
      }
    ],
    "ReturnTypes": []
  },
  {
    "ContainingType": "Code1.Controllers.WebServiceController",
    "Method": "DeleteMessage",
    "RelativePath": "api/WebService/message/{messageId}/{userId}",
    "HttpMethod": "DELETE",
    "IsController": true,
    "Order": 0,
    "Parameters": [
      {
        "Name": "messageId",
        "Type": "System.String",
        "IsRequired": true
      },
      {
        "Name": "userId",
        "Type": "System.String",
        "IsRequired": true
      }
    ],
    "ReturnTypes": []
  },
  {
    "ContainingType": "Code1.Controllers.WebServiceController",
    "Method": "SetMessageRead",
    "RelativePath": "api/WebService/message/read",
    "HttpMethod": "POST",
    "IsController": true,
    "Order": 0,
    "Parameters": [
      {
        "Name": "request",
        "Type": "Code1.Controllers.SetMessageReadRequest",
        "IsRequired": true
      }
    ],
    "ReturnTypes": []
  },
  {
    "ContainingType": "Code1.Controllers.WebServiceController",
    "Method": "GetUserMessages",
    "RelativePath": "api/WebService/messages/{userId}",
    "HttpMethod": "GET",
    "IsController": true,
    "Order": 0,
    "Parameters": [
      {
        "Name": "userId",
        "Type": "System.String",
        "IsRequired": true
      }
    ],
    "ReturnTypes": []
  },
  {
    "ContainingType": "Code1.Controllers.WebServiceController",
    "Method": "GetActiveMessages",
    "RelativePath": "api/WebService/messages/active/{userId}",
    "HttpMethod": "GET",
    "IsController": true,
    "Order": 0,
    "Parameters": [
      {
        "Name": "userId",
        "Type": "System.String",
        "IsRequired": true
      }
    ],
    "ReturnTypes": []
  },
  {
    "ContainingType": "Code1.Controllers.WebServiceController",
    "Method": "TestGetMessages",
    "RelativePath": "api/WebService/test/{userId}",
    "HttpMethod": "GET",
    "IsController": true,
    "Order": 0,
    "Parameters": [
      {
        "Name": "userId",
        "Type": "System.String",
        "IsRequired": true
      }
    ],
    "ReturnTypes": []
  },
  {
    "ContainingType": "Code1.Controllers.WebServiceController",
    "Method": "GetAllUsers",
    "RelativePath": "api/WebService/users",
    "HttpMethod": "GET",
    "IsController": true,
    "Order": 0,
    "Parameters": [],
    "ReturnTypes": []
  }
]